chatsheet/__init__.py
chatsheet/__main__.py
chatsheet/chatcsv.py
chatsheet/chatsheet.py
ChatSheet-0.0.1.dist-info/LICENSE
ChatSheet-0.0.1.dist-info/METADATA
ChatSheet-0.0.1.dist-info/WHEEL
ChatSheet-0.0.1.dist-info/entry_points.txt
ChatSheet-0.0.1.dist-info/top_level.txt
ChatSheet-0.0.1.dist-info/RECORD
